{
  "db_name": "PostgreSQL",
  "query": "\n        SELECT member_did \n        FROM members \n        WHERE convo_id = $1\n        AND member_did = $2 \n        AND left_at IS NULL\n        ",
  "describe": {
    "columns": [
      {
        "ordinal": 0,
        "name": "member_did",
        "type_info": "Text"
      }
    ],
    "parameters": {
      "Left": [
        "Text",
        "Text"
      ]
    },
    "nullable": [
      false
    ]
  },
  "hash": "583c73da57162b02ffa8f02a74b0381e6dafea09472e22679b0d3f7ad1fdb23b"
}
